Metadata-Version: 2.1
Name: teachable-pi-websocket
Version: 0.0.1
Summary: UNKNOWN
Home-page: https://github.com/lukaskirner/teachable-pi-websocket
Author: Lukas Kirner
Author-email: lukas.kirner@gmail.com
License: MIT
Download-URL: https://github.com/user/reponame/archive/v_01.tar.gz
Keywords: Teachable Machine,picamera,Raspberry Pi
Platform: UNKNOWN
Classifier: Development Status :: 5 - Production/Stable
Classifier: Intended Audience :: Developers
Classifier: Topic :: Software Development :: Build Tools
Classifier: License :: OSI Approved :: MIT License
Classifier: Programming Language :: Python :: 3
Classifier: Programming Language :: Python :: 3.4
Classifier: Programming Language :: Python :: 3.5
Classifier: Programming Language :: Python :: 3.6
